unus_data
