Metadata-Version: 2.1
Name: unus-data
Version: 0.1.5
Summary: A package to handle protein datacard for the protein project
Author: Li Minzhang
Author-email: limzh00@outlook.com
License: MIT
Platform: all
License-File: LICENSE
